minha_lib_aula02/__init__.py
minha_lib_aula02/core.py
minha_lib_aula02_package-1.0.0.dist-info/METADATA
minha_lib_aula02_package-1.0.0.dist-info/WHEEL
minha_lib_aula02_package-1.0.0.dist-info/top_level.txt
minha_lib_aula02_package-1.0.0.dist-info/RECORD
