Metadata-Version: 2.4
Name: minha_lib_aula02-package
Version: 1.0.0
Summary: Execercio para criar uma biblioteca
Home-page: https://github.com/nuvsolutions/minha_lib_aula02
Author: Wellington (RM364772)
Author-email: wellington@nuvsolutions.com.br
License: MIT
Dynamic: author
Dynamic: author-email
Dynamic: description
Dynamic: description-content-type
Dynamic: home-page
Dynamic: license
Dynamic: summary
